{
  "fixture_signature": "debug",
  "fixtures": [
    {
      "input": {
        "enemy_units": [
          {
            "archetype_id": "guardian",
            "team": "enemy",
            "x": 9.1,
            "y": 1.2
          }
        ],
        "player_units": [
          {
            "archetype_id": "mage",
            "team": "player",
            "x": 0.9,
            "y": 1.2
          }
        ],
        "record_events": true,
        "seed": 46.0,
        "tick_rate": 0.2
      },
      "name": "duel_mage_vs_guardian",
      "signature": "80679d6ebc59ebec98b99f840d1c3fae72ab990ebeb52d961486703966b4bda5",
      "summary": {
        "duration": 60.0,
        "enemy_comp": [
          "guardian"
        ],
        "player_comp": [
          "mage"
        ],
        "seed": 46.0,
        "unit_stats": [
          {
            "abilities": 5.0,
            "archetype": "mage",
            "assists": 0.0,
            "auto_attacks": 27.0,
            "damage_dealt": 582.2550000000001,
            "damage_dealt_ability": 128.25,
            "damage_dealt_auto": 300.1050000000002,
            "damage_dealt_ultimate": 153.9,
            "damage_mitigated": 5.0,
            "damage_received": 95.0,
            "deaths": 1.0,
            "healing_done": 0.0,
            "instance_id": 1.0,
            "kills": 2.0,
            "shielding_done": 0.0,
            "stuns": 0.0,
            "team": "player",
            "ultimates": 2.0,
            "won": true
          },
          {
            "abilities": 3.0,
            "archetype": "guardian",
            "assists": 0.0,
            "auto_attacks": 10.0,
            "damage_dealt": 95.0,
            "damage_dealt_ability": 0.0,
            "damage_dealt_auto": 95.0,
            "damage_dealt_ultimate": 0.0,
            "damage_mitigated": 255.6450000000002,
            "damage_received": 450.2550000000001,
            "deaths": 2.0,
            "healing_done": 0.0,
            "instance_id": 2.0,
            "kills": 1.0,
            "shielding_done": 132.0,
            "stuns": 0.0,
            "team": "enemy",
            "ultimates": 0.0,
            "won": false
          }
        ],
        "winner_team": "player"
      }
    }
  ],
  "rules_version": 1,
  "schema_signature": "7997cf6636e65be163fedd40d00e6c56dadd5eacb5b2e12c631f1c4e26198938",
  "schema_version": 1.0
}