{
	"fixture_signature": "4e1a6c0ee5b086926116a0aaa9ce9d586ce8f4179973306fd4f2188868a820c2",
	"fixtures": [
		{
			"input": {
				"enemy_units": [
					{
						"archetype_id": "guardian",
						"team": "enemy",
						"x": 8.0,
						"y": 5.0
					}
				],
				"player_units": [
					{
						"archetype_id": "swordsman",
						"team": "player",
						"x": 2.0,
						"y": 5.0
					}
				],
				"record_events": false,
				"seed": 101.0,
				"tick_rate": 0.1
			},
			"name": "duel_swordsman_vs_guardian",
			"signature": "004909b5ee470efa803c70b7fa2f758011455050f63b3dc5d526d27a51769bb2",
			"summary": {
				"duration": 63.0,
				"enemy_comp": [
					"guardian"
				],
				"player_comp": [
					"swordsman"
				],
				"seed": 101.0,
				"sudden_death_ticks": 30.0,
				"unit_stats": [
					{
						"abilities": 8.0,
						"archetype": "swordsman",
						"assists": 0.0,
						"auto_attacks": 35.0,
						"damage_dealt": 1392.4845714285705,
						"damage_dealt_ability": 450.0045714285713,
						"damage_dealt_auto": 563.7199999999998,
						"damage_dealt_passive": 0.0,
						"damage_dealt_ultimate": 378.75999999999993,
						"damage_mitigated": 97.99999999999994,
						"damage_received": 391.99999999999983,
						"deaths": 1.0,
						"healing_done": 0.0,
						"healing_done_ability": 0.0,
						"healing_done_auto": 0.0,
						"healing_done_passive": 0.0,
						"healing_done_ultimate": 0.0,
						"instance_id": 1.0,
						"kills": 2.0,
						"shielding_done": 0.0,
						"shielding_done_ability": 0.0,
						"shielding_done_auto": 0.0,
						"shielding_done_passive": 0.0,
						"shielding_done_ultimate": 0.0,
						"stuns": 0.0,
						"team": "player",
						"telemetry": {
							"hard_cc_seconds": 4.199999999999999,
							"schema": "teamfight.telemetry.v1"
						},
						"ultimates": 0.0,
						"won": true
					},
					{
						"abilities": 7.0,
						"archetype": "guardian",
						"assists": 0.0,
						"auto_attacks": 29.0,
						"damage_dealt": 391.99999999999983,
						"damage_dealt_ability": 0.0,
						"damage_dealt_auto": 324.79999999999984,
						"damage_dealt_passive": 0.0,
						"damage_dealt_ultimate": 67.2,
						"damage_mitigated": 655.2868571428567,
						"damage_received": 679.2813245385613,
						"deaths": 2.0,
						"healing_done": 0.0,
						"healing_done_ability": 0.0,
						"healing_done_auto": 0.0,
						"healing_done_passive": 0.0,
						"healing_done_ultimate": 0.0,
						"instance_id": 2.0,
						"kills": 1.0,
						"shielding_done": 980.0,
						"shielding_done_ability": 980.0,
						"shielding_done_auto": 0.0,
						"shielding_done_passive": 0.0,
						"shielding_done_ultimate": 0.0,
						"stuns": 2.0,
						"team": "enemy",
						"telemetry": {
							"hard_cc_seconds": 0.0,
							"schema": "teamfight.telemetry.v1"
						},
						"ultimates": 0.0,
						"won": false
					}
				],
				"winner_team": "player"
			}
		},
		{
			"input": {
				"enemy_units": [
					{
						"archetype_id": "guardian",
						"team": "enemy",
						"x": 8.0,
						"y": 5.0
					}
				],
				"player_units": [
					{
						"archetype_id": "archer",
						"team": "player",
						"x": 2.0,
						"y": 5.0
					}
				],
				"record_events": false,
				"seed": 202.0,
				"tick_rate": 0.1
			},
			"name": "duel_archer_vs_guardian",
			"signature": "de0db35ed4a97a5b2303fcb88823df5247b95f9f6e6539588e5f54d12e19e92e",
			"summary": {
				"duration": 60.0,
				"enemy_comp": [
					"guardian"
				],
				"player_comp": [
					"archer"
				],
				"seed": 202.0,
				"sudden_death_ticks": 0.0,
				"unit_stats": [
					{
						"abilities": 7.0,
						"archetype": "archer",
						"assists": 0.0,
						"auto_attacks": 45.0,
						"damage_dealt": 791.754325086626,
						"damage_dealt_ability": 112.56586237625004,
						"damage_dealt_auto": 592.043183890625,
						"damage_dealt_passive": 0.0,
						"damage_dealt_ultimate": 87.14527881975002,
						"damage_mitigated": 18.200000000000024,
						"damage_received": 345.80000000000007,
						"deaths": 2.0,
						"healing_done": 0.0,
						"healing_done_ability": 0.0,
						"healing_done_auto": 0.0,
						"healing_done_passive": 0.0,
						"healing_done_ultimate": 0.0,
						"instance_id": 1.0,
						"kills": 0.0,
						"shielding_done": 0.0,
						"shielding_done_ability": 0.0,
						"shielding_done_auto": 0.0,
						"shielding_done_passive": 0.0,
						"shielding_done_ultimate": 0.0,
						"stuns": 0.0,
						"team": "player",
						"telemetry": {
							"hard_cc_seconds": 0.0,
							"schema": "teamfight.telemetry.v1"
						},
						"ultimates": 0.0,
						"won": false
					},
					{
						"abilities": 5.0,
						"archetype": "guardian",
						"assists": 0.0,
						"auto_attacks": 20.0,
						"damage_dealt": 345.80000000000007,
						"damage_dealt_ability": 0.0,
						"damage_dealt_auto": 266.0000000000001,
						"damage_dealt_passive": 0.0,
						"damage_dealt_ultimate": 79.8,
						"damage_mitigated": 226.2056749133749,
						"damage_received": 306.01729678068574,
						"deaths": 0.0,
						"healing_done": 0.0,
						"healing_done_ability": 0.0,
						"healing_done_auto": 0.0,
						"healing_done_passive": 0.0,
						"healing_done_ultimate": 0.0,
						"instance_id": 2.0,
						"kills": 2.0,
						"shielding_done": 700.0,
						"shielding_done_ability": 700.0,
						"shielding_done_auto": 0.0,
						"shielding_done_passive": 0.0,
						"shielding_done_ultimate": 0.0,
						"stuns": 2.0,
						"team": "enemy",
						"telemetry": {
							"hard_cc_seconds": 0.0,
							"schema": "teamfight.telemetry.v1"
						},
						"ultimates": 0.0,
						"won": true
					}
				],
				"winner_team": "enemy"
			}
		},
		{
			"input": {
				"enemy_units": [
					{
						"archetype_id": "swordsman",
						"team": "enemy",
						"x": 8.0,
						"y": 4.5
					},
					{
						"archetype_id": "archer",
						"team": "enemy",
						"x": 8.4,
						"y": 5.5
					}
				],
				"player_units": [
					{
						"archetype_id": "guardian",
						"team": "player",
						"x": 2.0,
						"y": 4.5
					},
					{
						"archetype_id": "cleric",
						"team": "player",
						"x": 1.6,
						"y": 5.5
					}
				],
				"record_events": false,
				"seed": 303.0,
				"tick_rate": 0.1
			},
			"name": "support_clash",
			"signature": "916d73acbff6774fd678c6a9e498869c35b2826b7954c89c849d77cf997363b1",
			"summary": {
				"duration": 60.0,
				"enemy_comp": [
					"swordsman",
					"archer"
				],
				"player_comp": [
					"guardian",
					"cleric"
				],
				"seed": 303.0,
				"sudden_death_ticks": 0.0,
				"unit_stats": [
					{
						"abilities": 6.0,
						"archetype": "guardian",
						"assists": 0.0,
						"auto_attacks": 23.0,
						"damage_dealt": 291.1999999999999,
						"damage_dealt_ability": 0.0,
						"damage_dealt_auto": 257.5999999999999,
						"damage_dealt_passive": 0.0,
						"damage_dealt_ultimate": 33.6,
						"damage_mitigated": 452.20571187162017,
						"damage_received": 1249.248900187559,
						"deaths": 2.0,
						"healing_done": 0.0,
						"healing_done_ability": 0.0,
						"healing_done_auto": 0.0,
						"healing_done_passive": 0.0,
						"healing_done_ultimate": 0.0,
						"instance_id": 1.0,
						"kills": 1.0,
						"shielding_done": 480.0,
						"shielding_done_ability": 480.0,
						"shielding_done_auto": 0.0,
						"shielding_done_passive": 0.0,
						"shielding_done_ultimate": 0.0,
						"stuns": 1.0,
						"team": "player",
						"telemetry": {
							"hard_cc_seconds": 0.0,
							"schema": "teamfight.telemetry.v1"
						},
						"ultimates": 0.0,
						"won": false
					},
					{
						"abilities": 25.0,
						"archetype": "cleric",
						"assists": 0.0,
						"auto_attacks": 0.0,
						"damage_dealt": 0.0,
						"damage_dealt_ability": 0.0,
						"damage_dealt_auto": 0.0,
						"damage_dealt_passive": 0.0,
						"damage_dealt_ultimate": 0.0,
						"damage_mitigated": 10.666578701976473,
						"damage_received": 401.0629193007984,
						"deaths": 2.0,
						"healing_done": 504.6353171481141,
						"healing_done_ability": 392.648,
						"healing_done_auto": 0.0,
						"healing_done_passive": 0.0,
						"healing_done_ultimate": 111.98731714811407,
						"instance_id": 2.0,
						"kills": 0.0,
						"shielding_done": 0.0,
						"shielding_done_ability": 0.0,
						"shielding_done_auto": 0.0,
						"shielding_done_passive": 0.0,
						"shielding_done_ultimate": 0.0,
						"stuns": 0.0,
						"team": "player",
						"telemetry": {
							"hard_cc_seconds": 0.0,
							"schema": "teamfight.telemetry.v1"
						},
						"ultimates": 0.0,
						"won": false
					},
					{
						"abilities": 8.0,
						"archetype": "swordsman",
						"assists": 2.0,
						"auto_attacks": 28.0,
						"damage_dealt": 1134.12464873652,
						"damage_dealt_ability": 370.941218251468,
						"damage_dealt_auto": 456.9259175804323,
						"damage_dealt_passive": 0.0,
						"damage_dealt_ultimate": 306.25751290462017,
						"damage_mitigated": 72.79999999999995,
						"damage_received": 291.1999999999999,
						"deaths": 1.0,
						"healing_done": 0.0,
						"healing_done_ability": 0.0,
						"healing_done_auto": 0.0,
						"healing_done_passive": 0.0,
						"healing_done_ultimate": 0.0,
						"instance_id": 3.0,
						"kills": 2.0,
						"shielding_done": 0.0,
						"shielding_done_ability": 0.0,
						"shielding_done_auto": 0.0,
						"shielding_done_passive": 0.0,
						"shielding_done_ultimate": 0.0,
						"stuns": 0.0,
						"team": "enemy",
						"telemetry": {
							"hard_cc_seconds": 3.4999999999999996,
							"schema": "teamfight.telemetry.v1"
						},
						"ultimates": 0.0,
						"won": true
					},
					{
						"abilities": 9.0,
						"archetype": "archer",
						"assists": 2.0,
						"auto_attacks": 41.0,
						"damage_dealt": 935.3019123683428,
						"damage_dealt_ability": 153.64161677206238,
						"damage_dealt_auto": 630.7032559355617,
						"damage_dealt_passive": 0.0,
						"damage_dealt_ultimate": 150.95703966071954,
						"damage_mitigated": 0.0,
						"damage_received": 0.0,
						"deaths": 0.0,
						"healing_done": 0.0,
						"healing_done_ability": 0.0,
						"healing_done_auto": 0.0,
						"healing_done_passive": 0.0,
						"healing_done_ultimate": 0.0,
						"instance_id": 4.0,
						"kills": 2.0,
						"shielding_done": 0.0,
						"shielding_done_ability": 0.0,
						"shielding_done_auto": 0.0,
						"shielding_done_passive": 0.0,
						"shielding_done_ultimate": 0.0,
						"stuns": 0.0,
						"team": "enemy",
						"telemetry": {
							"hard_cc_seconds": 0.0,
							"schema": "teamfight.telemetry.v1"
						},
						"ultimates": 0.0,
						"won": true
					}
				],
				"winner_team": "enemy"
			}
		},
		{
			"input": {
				"enemy_units": [
					{
						"archetype_id": "artillery",
						"team": "enemy",
						"x": 8.0,
						"y": 4.5
					},
					{
						"archetype_id": "guardian",
						"team": "enemy",
						"x": 8.4,
						"y": 5.5
					}
				],
				"player_units": [
					{
						"archetype_id": "rogue",
						"team": "player",
						"x": 2.0,
						"y": 4.5
					},
					{
						"archetype_id": "wizard",
						"team": "player",
						"x": 1.6,
						"y": 5.5
					}
				],
				"record_events": false,
				"seed": 404.0,
				"tick_rate": 0.1
			},
			"name": "backline_skirmish",
			"signature": "2fdd2d19a77e284b3833964c7e45b3a77e2e6251b3648aa10eb86d716bae04ff",
			"summary": {
				"duration": 60.0,
				"enemy_comp": [
					"artillery",
					"guardian"
				],
				"player_comp": [
					"rogue",
					"wizard"
				],
				"seed": 404.0,
				"sudden_death_ticks": 0.0,
				"unit_stats": [
					{
						"abilities": 8.0,
						"archetype": "rogue",
						"assists": 0.0,
						"auto_attacks": 26.0,
						"damage_dealt": 1076.652,
						"damage_dealt_ability": 360.828,
						"damage_dealt_auto": 605.6639999999999,
						"damage_dealt_passive": 0.0,
						"damage_dealt_ultimate": 110.16,
						"damage_mitigated": 43.8765,
						"damage_received": 394.88850000000014,
						"deaths": 1.0,
						"healing_done": 0.0,
						"healing_done_ability": 0.0,
						"healing_done_auto": 0.0,
						"healing_done_passive": 0.0,
						"healing_done_ultimate": 0.0,
						"instance_id": 1.0,
						"kills": 4.0,
						"shielding_done": 0.0,
						"shielding_done_ability": 0.0,
						"shielding_done_auto": 0.0,
						"shielding_done_passive": 0.0,
						"shielding_done_ultimate": 0.0,
						"stuns": 0.0,
						"team": "player",
						"telemetry": {
							"hard_cc_seconds": 2.0000000000000004,
							"schema": "teamfight.telemetry.v1"
						},
						"ultimates": 0.0,
						"won": true
					},
					{
						"abilities": 5.0,
						"archetype": "wizard",
						"assists": 1.0,
						"auto_attacks": 30.0,
						"damage_dealt": 782.0000000000003,
						"damage_dealt_ability": 61.2,
						"damage_dealt_auto": 380.8000000000001,
						"damage_dealt_passive": 0.0,
						"damage_dealt_ultimate": 340.0,
						"damage_mitigated": 8.749250000000012,
						"damage_received": 166.23575,
						"deaths": 1.0,
						"healing_done": 0.0,
						"healing_done_ability": 0.0,
						"healing_done_auto": 0.0,
						"healing_done_passive": 0.0,
						"healing_done_ultimate": 0.0,
						"instance_id": 2.0,
						"kills": 1.0,
						"shielding_done": 0.0,
						"shielding_done_ability": 0.0,
						"shielding_done_auto": 0.0,
						"shielding_done_passive": 0.0,
						"shielding_done_ultimate": 0.0,
						"stuns": 0.0,
						"team": "player",
						"telemetry": {
							"hard_cc_seconds": 0.0,
							"schema": "teamfight.telemetry.v1"
						},
						"ultimates": 0.0,
						"won": true
					},
					{
						"abilities": 6.0,
						"archetype": "artillery",
						"assists": 1.0,
						"auto_attacks": 17.0,
						"damage_dealt": 366.52425000000005,
						"damage_dealt_ability": 87.21,
						"damage_dealt_auto": 191.37749999999997,
						"damage_dealt_passive": 87.93675000000002,
						"damage_dealt_ultimate": 0.0,
						"damage_mitigated": 36.18000000000004,
						"damage_received": 623.1712744761272,
						"deaths": 3.0,
						"healing_done": 0.0,
						"healing_done_ability": 0.0,
						"healing_done_auto": 0.0,
						"healing_done_passive": 0.0,
						"healing_done_ultimate": 0.0,
						"instance_id": 3.0,
						"kills": 0.0,
						"shielding_done": 0.0,
						"shielding_done_ability": 0.0,
						"shielding_done_auto": 0.0,
						"shielding_done_passive": 0.0,
						"shielding_done_ultimate": 0.0,
						"stuns": 4.0,
						"team": "enemy",
						"telemetry": {
							"hard_cc_seconds": 0.0,
							"schema": "teamfight.telemetry.v1"
						},
						"ultimates": 0.0,
						"won": false
					},
					{
						"abilities": 4.0,
						"archetype": "guardian",
						"assists": 0.0,
						"auto_attacks": 16.0,
						"damage_dealt": 194.60000000000005,
						"damage_dealt_ability": 0.0,
						"damage_dealt_auto": 194.60000000000005,
						"damage_dealt_passive": 0.0,
						"damage_dealt_ultimate": 0.0,
						"damage_mitigated": 551.1679999999998,
						"damage_received": 909.2168537519442,
						"deaths": 2.0,
						"healing_done": 0.0,
						"healing_done_ability": 0.0,
						"healing_done_auto": 0.0,
						"healing_done_passive": 0.0,
						"healing_done_ultimate": 0.0,
						"instance_id": 4.0,
						"kills": 2.0,
						"shielding_done": 434.0,
						"shielding_done_ability": 434.0,
						"shielding_done_auto": 0.0,
						"shielding_done_passive": 0.0,
						"shielding_done_ultimate": 0.0,
						"stuns": 0.0,
						"team": "enemy",
						"telemetry": {
							"hard_cc_seconds": 0.0,
							"schema": "teamfight.telemetry.v1"
						},
						"ultimates": 0.0,
						"won": false
					}
				],
				"winner_team": "player"
			}
		},
		{
			"input": {
				"enemy_units": [
					{
						"archetype_id": "guardian",
						"team": "enemy",
						"x": 8.0,
						"y": 3.0
					},
					{
						"archetype_id": "swordsman",
						"team": "enemy",
						"x": 8.0,
						"y": 4.0
					},
					{
						"archetype_id": "artillery",
						"team": "enemy",
						"x": 8.6,
						"y": 5.0
					},
					{
						"archetype_id": "warlock",
						"team": "enemy",
						"x": 8.6,
						"y": 6.0
					},
					{
						"archetype_id": "rogue",
						"team": "enemy",
						"x": 8.6,
						"y": 7.0
					}
				],
				"player_units": [
					{
						"archetype_id": "guardian",
						"team": "player",
						"x": 2.0,
						"y": 3.0
					},
					{
						"archetype_id": "swordsman",
						"team": "player",
						"x": 2.0,
						"y": 4.0
					},
					{
						"archetype_id": "cleric",
						"team": "player",
						"x": 1.4,
						"y": 5.0
					},
					{
						"archetype_id": "wizard",
						"team": "player",
						"x": 1.4,
						"y": 6.0
					},
					{
						"archetype_id": "archer",
						"team": "player",
						"x": 1.4,
						"y": 7.0
					}
				],
				"record_events": false,
				"seed": 505.0,
				"tick_rate": 0.1
			},
			"name": "mixed_5v5",
			"signature": "86aaa07a85b6a59ece314b8a5dc26922b43a2505743ba721166089f11454f750",
			"summary": {
				"duration": 60.0,
				"enemy_comp": [
					"guardian",
					"swordsman",
					"artillery",
					"warlock",
					"rogue"
				],
				"player_comp": [
					"guardian",
					"swordsman",
					"cleric",
					"wizard",
					"archer"
				],
				"seed": 505.0,
				"sudden_death_ticks": 0.0,
				"unit_stats": [
					{
						"abilities": 8.0,
						"archetype": "guardian",
						"assists": 13.0,
						"auto_attacks": 30.0,
						"damage_dealt": 462.1781070391995,
						"damage_dealt_ability": 0.0,
						"damage_dealt_auto": 353.0398581429495,
						"damage_dealt_passive": 0.0,
						"damage_dealt_ultimate": 109.13824889625,
						"damage_mitigated": 255.18495999999988,
						"damage_received": 157.2201435163736,
						"deaths": 0.0,
						"healing_done": 0.0,
						"healing_done_ability": 0.0,
						"healing_done_auto": 0.0,
						"healing_done_passive": 0.0,
						"healing_done_ultimate": 0.0,
						"instance_id": 1.0,
						"kills": 0.0,
						"shielding_done": 1024.0,
						"shielding_done_ability": 1024.0,
						"shielding_done_auto": 0.0,
						"shielding_done_passive": 0.0,
						"shielding_done_ultimate": 0.0,
						"stuns": 3.0,
						"team": "player",
						"telemetry": {
							"hard_cc_seconds": 1.5000000000000002,
							"schema": "teamfight.telemetry.v1"
						},
						"ultimates": 0.0,
						"won": true
					},
					{
						"abilities": 9.0,
						"archetype": "swordsman",
						"assists": 2.0,
						"auto_attacks": 42.0,
						"damage_dealt": 2323.285729675428,
						"damage_dealt_ability": 674.5522962637529,
						"damage_dealt_auto": 957.6770263338296,
						"damage_dealt_passive": 0.0,
						"damage_dealt_ultimate": 691.0564070778466,
						"damage_mitigated": 225.27440000000024,
						"damage_received": 521.5599258173879,
						"deaths": 0.0,
						"healing_done": 0.0,
						"healing_done_ability": 0.0,
						"healing_done_auto": 0.0,
						"healing_done_passive": 0.0,
						"healing_done_ultimate": 0.0,
						"instance_id": 2.0,
						"kills": 7.0,
						"shielding_done": 0.0,
						"shielding_done_ability": 0.0,
						"shielding_done_auto": 0.0,
						"shielding_done_passive": 0.0,
						"shielding_done_ultimate": 0.0,
						"stuns": 0.0,
						"team": "player",
						"telemetry": {
							"hard_cc_seconds": 0.5,
							"schema": "teamfight.telemetry.v1"
						},
						"ultimates": 0.0,
						"won": true
					},
					{
						"abilities": 26.0,
						"archetype": "cleric",
						"assists": 7.0,
						"auto_attacks": 0.0,
						"damage_dealt": 0.0,
						"damage_dealt_ability": 0.0,
						"damage_dealt_auto": 0.0,
						"damage_dealt_passive": 0.0,
						"damage_dealt_ultimate": 0.0,
						"damage_mitigated": 39.25120000000001,
						"damage_received": 460.4088,
						"deaths": 1.0,
						"healing_done": 884.7256885364284,
						"healing_done_ability": 459.52535,
						"healing_done_auto": 0.0,
						"healing_done_passive": 0.0,
						"healing_done_ultimate": 425.2003385364284,
						"instance_id": 3.0,
						"kills": 0.0,
						"shielding_done": 0.0,
						"shielding_done_ability": 0.0,
						"shielding_done_auto": 0.0,
						"shielding_done_passive": 0.0,
						"shielding_done_ultimate": 0.0,
						"stuns": 0.0,
						"team": "player",
						"telemetry": {
							"hard_cc_seconds": 1.5000000000000002,
							"schema": "teamfight.telemetry.v1"
						},
						"ultimates": 0.0,
						"won": true
					},
					{
						"abilities": 6.0,
						"archetype": "wizard",
						"assists": 2.0,
						"auto_attacks": 30.0,
						"damage_dealt": 1036.3129789249915,
						"damage_dealt_ability": 133.5,
						"damage_dealt_auto": 467.21297892499155,
						"damage_dealt_passive": 0.0,
						"damage_dealt_ultimate": 435.6,
						"damage_mitigated": 18.705000000000023,
						"damage_received": 308.5949999999999,
						"deaths": 0.0,
						"healing_done": 0.0,
						"healing_done_ability": 0.0,
						"healing_done_auto": 0.0,
						"healing_done_passive": 0.0,
						"healing_done_ultimate": 0.0,
						"instance_id": 4.0,
						"kills": 5.0,
						"shielding_done": 0.0,
						"shielding_done_ability": 0.0,
						"shielding_done_auto": 0.0,
						"shielding_done_passive": 0.0,
						"shielding_done_ultimate": 0.0,
						"stuns": 0.0,
						"team": "player",
						"telemetry": {
							"hard_cc_seconds": 0.0,
							"schema": "teamfight.telemetry.v1"
						},
						"ultimates": 0.0,
						"won": true
					},
					{
						"abilities": 8.0,
						"archetype": "archer",
						"assists": 8.0,
						"auto_attacks": 39.0,
						"damage_dealt": 1072.316278269764,
						"damage_dealt_ability": 111.6555416661875,
						"damage_dealt_auto": 555.6781690980271,
						"damage_dealt_passive": 0.0,
						"damage_dealt_ultimate": 404.9825675055493,
						"damage_mitigated": 11.260000000000012,
						"damage_received": 213.93999999999997,
						"deaths": 1.0,
						"healing_done": 0.0,
						"healing_done_ability": 0.0,
						"healing_done_auto": 0.0,
						"healing_done_passive": 0.0,
						"healing_done_ultimate": 0.0,
						"instance_id": 5.0,
						"kills": 2.0,
						"shielding_done": 0.0,
						"shielding_done_ability": 0.0,
						"shielding_done_auto": 0.0,
						"shielding_done_passive": 0.0,
						"shielding_done_ultimate": 0.0,
						"stuns": 0.0,
						"team": "player",
						"telemetry": {
							"hard_cc_seconds": 0.5,
							"schema": "teamfight.telemetry.v1"
						},
						"ultimates": 0.0,
						"won": true
					},
					{
						"abilities": 3.0,
						"archetype": "guardian",
						"assists": 0.0,
						"auto_attacks": 20.0,
						"damage_dealt": 217.27999999999997,
						"damage_dealt_ability": 0.0,
						"damage_dealt_auto": 217.27999999999997,
						"damage_dealt_passive": 0.0,
						"damage_dealt_ultimate": 0.0,
						"damage_mitigated": 337.80780598181104,
						"damage_received": 1469.5169820003698,
						"deaths": 4.0,
						"healing_done": 0.0,
						"healing_done_ability": 0.0,
						"healing_done_auto": 0.0,
						"healing_done_passive": 0.0,
						"healing_done_ultimate": 0.0,
						"instance_id": 6.0,
						"kills": 0.0,
						"shielding_done": 367.1835,
						"shielding_done_ability": 367.1835,
						"shielding_done_auto": 0.0,
						"shielding_done_passive": 0.0,
						"shielding_done_ultimate": 0.0,
						"stuns": 0.0,
						"team": "enemy",
						"telemetry": {
							"hard_cc_seconds": 0.0,
							"schema": "teamfight.telemetry.v1"
						},
						"ultimates": 0.0,
						"won": false
					},
					{
						"abilities": 5.0,
						"archetype": "swordsman",
						"assists": 0.0,
						"auto_attacks": 18.0,
						"damage_dealt": 642.6056000000001,
						"damage_dealt_ability": 324.44560000000047,
						"damage_dealt_auto": 318.1600000000001,
						"damage_dealt_passive": 0.0,
						"damage_dealt_ultimate": 0.0,
						"damage_mitigated": 274.9593316052335,
						"damage_received": 1339.6996398233382,
						"deaths": 4.0,
						"healing_done": 0.0,
						"healing_done_ability": 0.0,
						"healing_done_auto": 0.0,
						"healing_done_passive": 0.0,
						"healing_done_ultimate": 0.0,
						"instance_id": 7.0,
						"kills": 0.0,
						"shielding_done": 0.0,
						"shielding_done_ability": 0.0,
						"shielding_done_auto": 0.0,
						"shielding_done_passive": 0.0,
						"shielding_done_ultimate": 0.0,
						"stuns": 0.0,
						"team": "enemy",
						"telemetry": {
							"hard_cc_seconds": 1.8000000000000005,
							"schema": "teamfight.telemetry.v1"
						},
						"ultimates": 0.0,
						"won": false
					},
					{
						"abilities": 8.0,
						"archetype": "artillery",
						"assists": 0.0,
						"auto_attacks": 19.0,
						"damage_dealt": 665.0828399999996,
						"damage_dealt_ability": 158.81909999999996,
						"damage_dealt_auto": 257.7539999999999,
						"damage_dealt_passive": 161.63888999999995,
						"damage_dealt_ultimate": 86.87084999999999,
						"damage_mitigated": 1.6153491375000006,
						"damage_received": 108.5446508625,
						"deaths": 0.0,
						"healing_done": 0.0,
						"healing_done_ability": 0.0,
						"healing_done_auto": 0.0,
						"healing_done_passive": 0.0,
						"healing_done_ultimate": 0.0,
						"instance_id": 8.0,
						"kills": 0.0,
						"shielding_done": 0.0,
						"shielding_done_ability": 0.0,
						"shielding_done_auto": 0.0,
						"shielding_done_passive": 0.0,
						"shielding_done_ultimate": 0.0,
						"stuns": 8.0,
						"team": "enemy",
						"telemetry": {
							"hard_cc_seconds": 0.0,
							"schema": "teamfight.telemetry.v1"
						},
						"ultimates": 0.0,
						"won": false
					},
					{
						"abilities": 7.0,
						"archetype": "warlock",
						"assists": 1.0,
						"auto_attacks": 7.0,
						"damage_dealt": 502.6050000000001,
						"damage_dealt_ability": 411.8850000000001,
						"damage_dealt_auto": 90.72,
						"damage_dealt_passive": 0.0,
						"damage_dealt_ultimate": 0.0,
						"damage_mitigated": 89.15640227190865,
						"damage_received": 730.5530739738417,
						"deaths": 2.0,
						"healing_done": 132.5475,
						"healing_done_ability": 132.5475,
						"healing_done_auto": 0.0,
						"healing_done_passive": 0.0,
						"healing_done_ultimate": 0.0,
						"instance_id": 9.0,
						"kills": 1.0,
						"shielding_done": 0.0,
						"shielding_done_ability": 0.0,
						"shielding_done_auto": 0.0,
						"shielding_done_passive": 0.0,
						"shielding_done_ultimate": 0.0,
						"stuns": 0.0,
						"team": "enemy",
						"telemetry": {
							"hard_cc_seconds": 2.2000000000000006,
							"schema": "teamfight.telemetry.v1"
						},
						"ultimates": 0.0,
						"won": false
					},
					{
						"abilities": 4.0,
						"archetype": "rogue",
						"assists": 0.0,
						"auto_attacks": 8.0,
						"damage_dealt": 398.7359999999999,
						"damage_dealt_ability": 199.368,
						"damage_dealt_auto": 199.368,
						"damage_dealt_passive": 0.0,
						"damage_dealt_ultimate": 0.0,
						"damage_mitigated": 80.8714456655912,
						"damage_received": 914.5485543344088,
						"deaths": 4.0,
						"healing_done": 0.0,
						"healing_done_ability": 0.0,
						"healing_done_auto": 0.0,
						"healing_done_passive": 0.0,
						"healing_done_ultimate": 0.0,
						"instance_id": 10.0,
						"kills": 1.0,
						"shielding_done": 0.0,
						"shielding_done_ability": 0.0,
						"shielding_done_auto": 0.0,
						"shielding_done_passive": 0.0,
						"shielding_done_ultimate": 0.0,
						"stuns": 0.0,
						"team": "enemy",
						"telemetry": {
							"hard_cc_seconds": 0.0,
							"schema": "teamfight.telemetry.v1"
						},
						"ultimates": 0.0,
						"won": false
					}
				],
				"winner_team": "player"
			}
		},
		{
			"input": {
				"enemy_units": [
					{
						"archetype_id": "disarmer",
						"team": "enemy",
						"x": 8.0,
						"y": 3.0
					},
					{
						"archetype_id": "windcaller",
						"team": "enemy",
						"x": 8.0,
						"y": 4.0
					},
					{
						"archetype_id": "guardian",
						"team": "enemy",
						"x": 8.6,
						"y": 5.0
					},
					{
						"archetype_id": "oracle",
						"team": "enemy",
						"x": 8.6,
						"y": 6.0
					},
					{
						"archetype_id": "cleric",
						"team": "enemy",
						"x": 8.6,
						"y": 7.0
					}
				],
				"player_units": [
					{
						"archetype_id": "colossus",
						"team": "player",
						"x": 2.0,
						"y": 3.0
					},
					{
						"archetype_id": "earthbender",
						"team": "player",
						"x": 2.0,
						"y": 4.0
					},
					{
						"archetype_id": "frost_mage",
						"team": "player",
						"x": 1.4,
						"y": 5.0
					},
					{
						"archetype_id": "silencer",
						"team": "player",
						"x": 1.4,
						"y": 6.0
					},
					{
						"archetype_id": "mirror_knight",
						"team": "player",
						"x": 1.4,
						"y": 7.0
					}
				],
				"record_events": false,
				"seed": 606.0,
				"tick_rate": 0.1
			},
			"name": "effect_control_wall",
			"signature": "dd93c7a3b62e275d3a4a216215141bafd8eb290be2e690b14c00dfa28080d8e1",
			"summary": {
				"duration": 60.0,
				"enemy_comp": [
					"disarmer",
					"windcaller",
					"guardian",
					"oracle",
					"cleric"
				],
				"player_comp": [
					"colossus",
					"earthbender",
					"frost_mage",
					"silencer",
					"mirror_knight"
				],
				"seed": 606.0,
				"sudden_death_ticks": 0.0,
				"unit_stats": [
					{
						"abilities": 8.0,
						"archetype": "colossus",
						"assists": 0.0,
						"auto_attacks": 19.0,
						"damage_dealt": 306.69599999999986,
						"damage_dealt_ability": 100.38600000000002,
						"damage_dealt_auto": 180.96000000000004,
						"damage_dealt_passive": 0.0,
						"damage_dealt_ultimate": 25.35,
						"damage_mitigated": 436.5855000000002,
						"damage_received": 540.6344999999999,
						"deaths": 1.0,
						"healing_done": 0.0,
						"healing_done_ability": 0.0,
						"healing_done_auto": 0.0,
						"healing_done_passive": 0.0,
						"healing_done_ultimate": 0.0,
						"instance_id": 1.0,
						"kills": 0.0,
						"shielding_done": 0.0,
						"shielding_done_ability": 0.0,
						"shielding_done_auto": 0.0,
						"shielding_done_passive": 0.0,
						"shielding_done_ultimate": 0.0,
						"stuns": 1.0,
						"team": "player",
						"telemetry": {
							"hard_cc_seconds": 0.0,
							"schema": "teamfight.telemetry.v1"
						},
						"ultimates": 0.0,
						"won": false
					},
					{
						"abilities": 10.0,
						"archetype": "earthbender",
						"assists": 0.0,
						"auto_attacks": 26.0,
						"damage_dealt": 478.5120000000003,
						"damage_dealt_ability": 106.08000000000004,
						"damage_dealt_auto": 212.1599999999999,
						"damage_dealt_passive": 0.0,
						"damage_dealt_ultimate": 160.272,
						"damage_mitigated": 291.36999999999995,
						"damage_received": 247.93000000000004,
						"deaths": 0.0,
						"healing_done": 0.0,
						"healing_done_ability": 0.0,
						"healing_done_auto": 0.0,
						"healing_done_passive": 0.0,
						"healing_done_ultimate": 0.0,
						"instance_id": 2.0,
						"kills": 0.0,
						"shielding_done": 0.0,
						"shielding_done_ability": 0.0,
						"shielding_done_auto": 0.0,
						"shielding_done_passive": 0.0,
						"shielding_done_ultimate": 0.0,
						"stuns": 0.0,
						"team": "player",
						"telemetry": {
							"hard_cc_seconds": 3.4999999999999996,
							"schema": "teamfight.telemetry.v1"
						},
						"ultimates": 0.0,
						"won": false
					},
					{
						"abilities": 8.0,
						"archetype": "frost_mage",
						"assists": 0.0,
						"auto_attacks": 22.0,
						"damage_dealt": 577.8900000000001,
						"damage_dealt_ability": 175.878,
						"damage_dealt_auto": 307.548,
						"damage_dealt_passive": 0.0,
						"damage_dealt_ultimate": 94.464,
						"damage_mitigated": 19.945,
						"damage_received": 144.355,
						"deaths": 1.0,
						"healing_done": 0.0,
						"healing_done_ability": 0.0,
						"healing_done_auto": 0.0,
						"healing_done_passive": 0.0,
						"healing_done_ultimate": 0.0,
						"instance_id": 3.0,
						"kills": 0.0,
						"shielding_done": 0.0,
						"shielding_done_ability": 0.0,
						"shielding_done_auto": 0.0,
						"shielding_done_passive": 0.0,
						"shielding_done_ultimate": 0.0,
						"stuns": 0.0,
						"team": "player",
						"telemetry": {
							"hard_cc_seconds": 0.0,
							"schema": "teamfight.telemetry.v1"
						},
						"ultimates": 0.0,
						"won": false
					},
					{
						"abilities": 2.0,
						"archetype": "silencer",
						"assists": 0.0,
						"auto_attacks": 1.0,
						"damage_dealt": 93.4728,
						"damage_dealt_ability": 67.9728,
						"damage_dealt_auto": 25.5,
						"damage_dealt_passive": 0.0,
						"damage_dealt_ultimate": 0.0,
						"damage_mitigated": 168.93099999999998,
						"damage_received": 879.769,
						"deaths": 4.0,
						"healing_done": 0.0,
						"healing_done_ability": 0.0,
						"healing_done_auto": 0.0,
						"healing_done_passive": 0.0,
						"healing_done_ultimate": 0.0,
						"instance_id": 4.0,
						"kills": 0.0,
						"shielding_done": 0.0,
						"shielding_done_ability": 0.0,
						"shielding_done_auto": 0.0,
						"shielding_done_passive": 0.0,
						"shielding_done_ultimate": 0.0,
						"stuns": 0.0,
						"team": "player",
						"telemetry": {
							"hard_cc_seconds": 1.0,
							"schema": "teamfight.telemetry.v1"
						},
						"ultimates": 0.0,
						"won": false
					},
					{
						"abilities": 9.0,
						"archetype": "mirror_knight",
						"assists": 0.0,
						"auto_attacks": 29.0,
						"damage_dealt": 612.1916249999995,
						"damage_dealt_ability": 31.595999999999993,
						"damage_dealt_auto": 316.67999999999995,
						"damage_dealt_passive": 39.529799999999994,
						"damage_dealt_ultimate": 224.385825,
						"damage_mitigated": 334.19999999999993,
						"damage_received": 66.0353370275146,
						"deaths": 0.0,
						"healing_done": 0.0,
						"healing_done_ability": 0.0,
						"healing_done_auto": 0.0,
						"healing_done_passive": 0.0,
						"healing_done_ultimate": 0.0,
						"instance_id": 5.0,
						"kills": 0.0,
						"shielding_done": 945.0,
						"shielding_done_ability": 945.0,
						"shielding_done_auto": 0.0,
						"shielding_done_passive": 0.0,
						"shielding_done_ultimate": 0.0,
						"stuns": 0.0,
						"team": "player",
						"telemetry": {
							"hard_cc_seconds": 0.0,
							"schema": "teamfight.telemetry.v1"
						},
						"ultimates": 0.0,
						"won": false
					},
					{
						"abilities": 10.0,
						"archetype": "disarmer",
						"assists": 0.0,
						"auto_attacks": 52.0,
						"damage_dealt": 846.1124999999993,
						"damage_dealt_ability": 188.8875,
						"damage_dealt_auto": 657.2249999999997,
						"damage_dealt_passive": 0.0,
						"damage_dealt_ultimate": 0.0,
						"damage_mitigated": 296.69547499999993,
						"damage_received": 809.1772681124211,
						"deaths": 0.0,
						"healing_done": 0.0,
						"healing_done_ability": 0.0,
						"healing_done_auto": 0.0,
						"healing_done_passive": 0.0,
						"healing_done_ultimate": 0.0,
						"instance_id": 6.0,
						"kills": 1.0,
						"shielding_done": 0.0,
						"shielding_done_ability": 0.0,
						"shielding_done_auto": 0.0,
						"shielding_done_passive": 0.0,
						"shielding_done_ultimate": 0.0,
						"stuns": 0.0,
						"team": "enemy",
						"telemetry": {
							"hard_cc_seconds": 2.0,
							"schema": "teamfight.telemetry.v1"
						},
						"ultimates": 0.0,
						"won": true
					},
					{
						"abilities": 7.0,
						"archetype": "windcaller",
						"assists": 0.0,
						"auto_attacks": 34.0,
						"damage_dealt": 846.9059999999997,
						"damage_dealt_ability": 119.016,
						"damage_dealt_auto": 466.63999999999976,
						"damage_dealt_passive": 0.0,
						"damage_dealt_ultimate": 261.25,
						"damage_mitigated": 60.55799999999999,
						"damage_received": 49.14053017640232,
						"deaths": 0.0,
						"healing_done": 0.0,
						"healing_done_ability": 0.0,
						"healing_done_auto": 0.0,
						"healing_done_passive": 0.0,
						"healing_done_ultimate": 0.0,
						"instance_id": 7.0,
						"kills": 5.0,
						"shielding_done": 170.0,
						"shielding_done_ability": 119.0,
						"shielding_done_auto": 0.0,
						"shielding_done_passive": 0.0,
						"shielding_done_ultimate": 51.0,
						"stuns": 0.0,
						"team": "enemy",
						"telemetry": {
							"hard_cc_seconds": 0.0,
							"schema": "teamfight.telemetry.v1"
						},
						"ultimates": 0.0,
						"won": true
					},
					{
						"abilities": 8.0,
						"archetype": "guardian",
						"assists": 5.0,
						"auto_attacks": 32.0,
						"damage_dealt": 326.2000000000001,
						"damage_dealt_ability": 0.0,
						"damage_dealt_auto": 241.7800000000001,
						"damage_dealt_passive": 0.0,
						"damage_dealt_ultimate": 84.42,
						"damage_mitigated": 252.92960000000005,
						"damage_received": 83.38103910923991,
						"deaths": 0.0,
						"healing_done": 0.0,
						"healing_done_ability": 0.0,
						"healing_done_auto": 0.0,
						"healing_done_passive": 0.0,
						"healing_done_ultimate": 0.0,
						"instance_id": 8.0,
						"kills": 0.0,
						"shielding_done": 885.0,
						"shielding_done_ability": 885.0,
						"shielding_done_auto": 0.0,
						"shielding_done_passive": 0.0,
						"shielding_done_ultimate": 0.0,
						"stuns": 3.0,
						"team": "enemy",
						"telemetry": {
							"hard_cc_seconds": 0.0,
							"schema": "teamfight.telemetry.v1"
						},
						"ultimates": 0.0,
						"won": true
					},
					{
						"abilities": 6.0,
						"archetype": "oracle",
						"assists": 6.0,
						"auto_attacks": 28.0,
						"damage_dealt": 294.77,
						"damage_dealt_ability": 0.0,
						"damage_dealt_auto": 294.77,
						"damage_dealt_passive": 0.0,
						"damage_dealt_ultimate": 0.0,
						"damage_mitigated": 18.150250000000018,
						"damage_received": 72.56231290064136,
						"deaths": 0.0,
						"healing_done": 264.9497586160551,
						"healing_done_ability": 0.0,
						"healing_done_auto": 0.0,
						"healing_done_passive": 0.0,
						"healing_done_ultimate": 264.9497586160551,
						"instance_id": 9.0,
						"kills": 0.0,
						"shielding_done": 518.25,
						"shielding_done_ability": 198.0,
						"shielding_done_auto": 0.0,
						"shielding_done_passive": 0.0,
						"shielding_done_ultimate": 320.25,
						"stuns": 0.0,
						"team": "enemy",
						"telemetry": {
							"hard_cc_seconds": 0.0,
							"schema": "teamfight.telemetry.v1"
						},
						"ultimates": 0.0,
						"won": true
					},
					{
						"abilities": 30.0,
						"archetype": "cleric",
						"assists": 3.0,
						"auto_attacks": 0.0,
						"damage_dealt": 0.0,
						"damage_dealt_ability": 0.0,
						"damage_dealt_auto": 0.0,
						"damage_dealt_passive": 0.0,
						"damage_dealt_ultimate": 0.0,
						"damage_mitigated": 4.428000000000003,
						"damage_received": 33.29898165172328,
						"deaths": 0.0,
						"healing_done": 667.0440125168535,
						"healing_done_ability": 525.6761771790943,
						"healing_done_auto": 0.0,
						"healing_done_passive": 0.0,
						"healing_done_ultimate": 141.36783533775912,
						"instance_id": 10.0,
						"kills": 0.0,
						"shielding_done": 0.0,
						"shielding_done_ability": 0.0,
						"shielding_done_auto": 0.0,
						"shielding_done_passive": 0.0,
						"shielding_done_ultimate": 0.0,
						"stuns": 0.0,
						"team": "enemy",
						"telemetry": {
							"hard_cc_seconds": 0.0,
							"schema": "teamfight.telemetry.v1"
						},
						"ultimates": 0.0,
						"won": true
					}
				],
				"winner_team": "enemy"
			}
		},
		{
			"input": {
				"enemy_units": [
					{
						"archetype_id": "paladin",
						"team": "enemy",
						"x": 8.0,
						"y": 3.0
					},
					{
						"archetype_id": "rogue",
						"team": "enemy",
						"x": 8.0,
						"y": 4.0
					},
					{
						"archetype_id": "berserker",
						"team": "enemy",
						"x": 8.6,
						"y": 5.0
					},
					{
						"archetype_id": "warlock",
						"team": "enemy",
						"x": 8.6,
						"y": 6.0
					},
					{
						"archetype_id": "valkyrie",
						"team": "enemy",
						"x": 8.6,
						"y": 7.0
					}
				],
				"player_units": [
					{
						"archetype_id": "ninja",
						"team": "player",
						"x": 2.0,
						"y": 3.0
					},
					{
						"archetype_id": "archer",
						"team": "player",
						"x": 2.0,
						"y": 4.0
					},
					{
						"archetype_id": "artillery",
						"team": "player",
						"x": 1.4,
						"y": 5.0
					},
					{
						"archetype_id": "wizard",
						"team": "player",
						"x": 1.4,
						"y": 6.0
					},
					{
						"archetype_id": "sniper",
						"team": "player",
						"x": 1.4,
						"y": 7.0
					}
				],
				"record_events": false,
				"seed": 707.0,
				"tick_rate": 0.1
			},
			"name": "effect_projectile_rush",
			"signature": "c98b5da0a982fffec2b8add0fae197419386b3ba927692d55fe04ddc208533dc",
			"summary": {
				"duration": 60.0,
				"enemy_comp": [
					"paladin",
					"rogue",
					"berserker",
					"warlock",
					"valkyrie"
				],
				"player_comp": [
					"ninja",
					"archer",
					"artillery",
					"wizard",
					"sniper"
				],
				"seed": 707.0,
				"sudden_death_ticks": 0.0,
				"unit_stats": [
					{
						"abilities": 6.0,
						"archetype": "ninja",
						"assists": 0.0,
						"auto_attacks": 29.0,
						"damage_dealt": 1008.992324998278,
						"damage_dealt_ability": 101.46330003460368,
						"damage_dealt_auto": 705.0290249636745,
						"damage_dealt_passive": 0.0,
						"damage_dealt_ultimate": 202.5,
						"damage_mitigated": 145.50000000000003,
						"damage_received": 856.4999999999999,
						"deaths": 4.0,
						"healing_done": 0.0,
						"healing_done_ability": 0.0,
						"healing_done_auto": 0.0,
						"healing_done_passive": 0.0,
						"healing_done_ultimate": 0.0,
						"instance_id": 1.0,
						"kills": 3.0,
						"shielding_done": 0.0,
						"shielding_done_ability": 0.0,
						"shielding_done_auto": 0.0,
						"shielding_done_passive": 0.0,
						"shielding_done_ultimate": 0.0,
						"stuns": 3.0,
						"team": "player",
						"telemetry": {
							"hard_cc_seconds": 0.7,
							"schema": "teamfight.telemetry.v1"
						},
						"ultimates": 0.0,
						"won": false
					},
					{
						"abilities": 7.0,
						"archetype": "archer",
						"assists": 1.0,
						"auto_attacks": 42.0,
						"damage_dealt": 846.0552032211972,
						"damage_dealt_ability": 102.7963182015341,
						"damage_dealt_auto": 551.670290911379,
						"damage_dealt_passive": 0.0,
						"damage_dealt_ultimate": 191.5885941082848,
						"damage_mitigated": 20.625000000000018,
						"damage_received": 391.87499999999994,
						"deaths": 2.0,
						"healing_done": 0.0,
						"healing_done_ability": 0.0,
						"healing_done_auto": 0.0,
						"healing_done_passive": 0.0,
						"healing_done_ultimate": 0.0,
						"instance_id": 2.0,
						"kills": 2.0,
						"shielding_done": 0.0,
						"shielding_done_ability": 0.0,
						"shielding_done_auto": 0.0,
						"shielding_done_passive": 0.0,
						"shielding_done_ultimate": 0.0,
						"stuns": 0.0,
						"team": "player",
						"telemetry": {
							"hard_cc_seconds": 0.0,
							"schema": "teamfight.telemetry.v1"
						},
						"ultimates": 0.0,
						"won": false
					},
					{
						"abilities": 6.0,
						"archetype": "artillery",
						"assists": 3.0,
						"auto_attacks": 16.0,
						"damage_dealt": 466.7960482397062,
						"damage_dealt_ability": 80.42699999999999,
						"damage_dealt_auto": 214.60005127937748,
						"damage_dealt_passive": 171.76899696032893,
						"damage_dealt_ultimate": 0.0,
						"damage_mitigated": 23.425000000000026,
						"damage_received": 445.0750000000001,
						"deaths": 3.0,
						"healing_done": 0.0,
						"healing_done_ability": 0.0,
						"healing_done_auto": 0.0,
						"healing_done_passive": 0.0,
						"healing_done_ultimate": 0.0,
						"instance_id": 3.0,
						"kills": 0.0,
						"shielding_done": 0.0,
						"shielding_done_ability": 0.0,
						"shielding_done_auto": 0.0,
						"shielding_done_passive": 0.0,
						"shielding_done_ultimate": 0.0,
						"stuns": 4.0,
						"team": "player",
						"telemetry": {
							"hard_cc_seconds": 0.5,
							"schema": "teamfight.telemetry.v1"
						},
						"ultimates": 0.0,
						"won": false
					},
					{
						"abilities": 3.0,
						"archetype": "wizard",
						"assists": 2.0,
						"auto_attacks": 30.0,
						"damage_dealt": 813.8941778749997,
						"damage_dealt_ability": 75.9,
						"damage_dealt_auto": 484.99417787499976,
						"damage_dealt_passive": 0.0,
						"damage_dealt_ultimate": 253.0,
						"damage_mitigated": 35.875000000000014,
						"damage_received": 807.6250000000001,
						"deaths": 4.0,
						"healing_done": 0.0,
						"healing_done_ability": 0.0,
						"healing_done_auto": 0.0,
						"healing_done_passive": 0.0,
						"healing_done_ultimate": 0.0,
						"instance_id": 4.0,
						"kills": 0.0,
						"shielding_done": 0.0,
						"shielding_done_ability": 0.0,
						"shielding_done_auto": 0.0,
						"shielding_done_passive": 0.0,
						"shielding_done_ultimate": 0.0,
						"stuns": 0.0,
						"team": "player",
						"telemetry": {
							"hard_cc_seconds": 1.0,
							"schema": "teamfight.telemetry.v1"
						},
						"ultimates": 0.0,
						"won": false
					},
					{
						"abilities": 6.0,
						"archetype": "sniper",
						"assists": 2.0,
						"auto_attacks": 24.0,
						"damage_dealt": 520.2308041561743,
						"damage_dealt_ability": 96.64499999999998,
						"damage_dealt_auto": 374.20080415617423,
						"damage_dealt_passive": 0.0,
						"damage_dealt_ultimate": 49.385,
						"damage_mitigated": 18.200000000000017,
						"damage_received": 437.80000000000007,
						"deaths": 3.0,
						"healing_done": 0.0,
						"healing_done_ability": 0.0,
						"healing_done_auto": 0.0,
						"healing_done_passive": 0.0,
						"healing_done_ultimate": 0.0,
						"instance_id": 5.0,
						"kills": 1.0,
						"shielding_done": 0.0,
						"shielding_done_ability": 0.0,
						"shielding_done_auto": 0.0,
						"shielding_done_passive": 0.0,
						"shielding_done_ultimate": 0.0,
						"stuns": 0.0,
						"team": "player",
						"telemetry": {
							"hard_cc_seconds": 0.5,
							"schema": "teamfight.telemetry.v1"
						},
						"ultimates": 0.0,
						"won": false
					},
					{
						"abilities": 7.0,
						"archetype": "paladin",
						"assists": 12.0,
						"auto_attacks": 23.0,
						"damage_dealt": 405.59999999999985,
						"damage_dealt_ability": 0.0,
						"damage_dealt_auto": 341.59999999999985,
						"damage_dealt_passive": 0.0,
						"damage_dealt_ultimate": 64.0,
						"damage_mitigated": 202.1930961577812,
						"damage_received": 482.5919038422191,
						"deaths": 0.0,
						"healing_done": 1073.8898200859687,
						"healing_done_ability": 415.305625,
						"healing_done_auto": 0.0,
						"healing_done_passive": 437.3466950859691,
						"healing_done_ultimate": 221.2375,
						"instance_id": 6.0,
						"kills": 0.0,
						"shielding_done": 0.0,
						"shielding_done_ability": 0.0,
						"shielding_done_auto": 0.0,
						"shielding_done_passive": 0.0,
						"shielding_done_ultimate": 0.0,
						"stuns": 0.0,
						"team": "enemy",
						"telemetry": {
							"hard_cc_seconds": 0.0,
							"schema": "teamfight.telemetry.v1"
						},
						"ultimates": 0.0,
						"won": true
					},
					{
						"abilities": 5.0,
						"archetype": "rogue",
						"assists": 0.0,
						"auto_attacks": 14.0,
						"damage_dealt": 718.1999999999997,
						"damage_dealt_ability": 205.2,
						"damage_dealt_auto": 359.0999999999999,
						"damage_dealt_passive": 0.0,
						"damage_dealt_ultimate": 153.9,
						"damage_mitigated": 48.83125114650206,
						"damage_received": 789.454248911171,
						"deaths": 3.0,
						"healing_done": 0.0,
						"healing_done_ability": 0.0,
						"healing_done_auto": 0.0,
						"healing_done_passive": 0.0,
						"healing_done_ultimate": 0.0,
						"instance_id": 7.0,
						"kills": 4.0,
						"shielding_done": 0.0,
						"shielding_done_ability": 0.0,
						"shielding_done_auto": 0.0,
						"shielding_done_passive": 0.0,
						"shielding_done_ultimate": 0.0,
						"stuns": 0.0,
						"team": "enemy",
						"telemetry": {
							"hard_cc_seconds": 0.5,
							"schema": "teamfight.telemetry.v1"
						},
						"ultimates": 0.0,
						"won": true
					},
					{
						"abilities": 9.0,
						"archetype": "berserker",
						"assists": 4.0,
						"auto_attacks": 30.0,
						"damage_dealt": 897.0000000000002,
						"damage_dealt_ability": 0.0,
						"damage_dealt_auto": 621.0000000000003,
						"damage_dealt_passive": 0.0,
						"damage_dealt_ultimate": 276.0,
						"damage_mitigated": 150.3204008046343,
						"damage_received": 478.6589868401739,
						"deaths": 0.0,
						"healing_done": 314.1800000000001,
						"healing_done_ability": 0.0,
						"healing_done_auto": 199.18000000000012,
						"healing_done_passive": 0.0,
						"healing_done_ultimate": 114.99999999999996,
						"instance_id": 8.0,
						"kills": 6.0,
						"shielding_done": 972.0,
						"shielding_done_ability": 972.0,
						"shielding_done_auto": 0.0,
						"shielding_done_passive": 0.0,
						"shielding_done_ultimate": 0.0,
						"stuns": 0.0,
						"team": "enemy",
						"telemetry": {
							"hard_cc_seconds": 1.0,
							"schema": "teamfight.telemetry.v1"
						},
						"ultimates": 0.0,
						"won": true
					},
					{
						"abilities": 7.0,
						"archetype": "warlock",
						"assists": 8.0,
						"auto_attacks": 3.0,
						"damage_dealt": 301.5,
						"damage_dealt_ability": 263.25,
						"damage_dealt_auto": 38.25,
						"damage_dealt_passive": 0.0,
						"damage_dealt_ultimate": 0.0,
						"damage_mitigated": 126.7821308689483,
						"damage_received": 887.2878691310514,
						"deaths": 2.0,
						"healing_done": 121.78125000000004,
						"healing_done_ability": 121.78125000000004,
						"healing_done_auto": 0.0,
						"healing_done_passive": 0.0,
						"healing_done_ultimate": 0.0,
						"instance_id": 9.0,
						"kills": 0.0,
						"shielding_done": 0.0,
						"shielding_done_ability": 0.0,
						"shielding_done_auto": 0.0,
						"shielding_done_passive": 0.0,
						"shielding_done_ultimate": 0.0,
						"stuns": 0.0,
						"team": "enemy",
						"telemetry": {
							"hard_cc_seconds": 1.5000000000000002,
							"schema": "teamfight.telemetry.v1"
						},
						"ultimates": 0.0,
						"won": true
					},
					{
						"abilities": 7.0,
						"archetype": "valkyrie",
						"assists": 4.0,
						"auto_attacks": 16.0,
						"damage_dealt": 616.5749999999999,
						"damage_dealt_ability": 180.97499999999997,
						"damage_dealt_auto": 273.6,
						"damage_dealt_passive": 162.0,
						"damage_dealt_ultimate": 0.0,
						"damage_mitigated": 137.16006258944995,
						"damage_received": 717.4349374105497,
						"deaths": 1.0,
						"healing_done": 161.99999999999997,
						"healing_done_ability": 0.0,
						"healing_done_auto": 0.0,
						"healing_done_passive": 161.99999999999997,
						"healing_done_ultimate": 0.0,
						"instance_id": 10.0,
						"kills": 6.0,
						"shielding_done": 0.0,
						"shielding_done_ability": 0.0,
						"shielding_done_auto": 0.0,
						"shielding_done_passive": 0.0,
						"shielding_done_ultimate": 0.0,
						"stuns": 7.0,
						"team": "enemy",
						"telemetry": {
							"hard_cc_seconds": 0.5,
							"schema": "teamfight.telemetry.v1"
						},
						"ultimates": 0.0,
						"won": true
					}
				],
				"winner_team": "enemy"
			}
		},
		{
			"input": {
				"enemy_units": [
					{
						"archetype_id": "monk",
						"team": "enemy",
						"x": 8.0,
						"y": 5.0
					}
				],
				"player_units": [
					{
						"archetype_id": "wraith",
						"team": "player",
						"x": 2.0,
						"y": 5.0
					}
				],
				"record_events": false,
				"seed": 808.0,
				"tick_rate": 0.1
			},
			"name": "duel_wraith_vs_monk",
			"signature": "91b27224407399a3d5f99c40b087068e3d09f4ef73d0d1c7c2f1630520868656",
			"summary": {
				"duration": 60.0,
				"enemy_comp": [
					"monk"
				],
				"player_comp": [
					"wraith"
				],
				"seed": 808.0,
				"sudden_death_ticks": 0.0,
				"unit_stats": [
					{
						"abilities": 6.0,
						"archetype": "wraith",
						"assists": 0.0,
						"auto_attacks": 20.0,
						"damage_dealt": 520.2600000000001,
						"damage_dealt_ability": 161.46,
						"damage_dealt_auto": 358.8,
						"damage_dealt_passive": 0.0,
						"damage_dealt_ultimate": 0.0,
						"damage_mitigated": 115.8111,
						"damage_received": 658.9539000000002,
						"deaths": 3.0,
						"healing_done": 0.0,
						"healing_done_ability": 0.0,
						"healing_done_auto": 0.0,
						"healing_done_passive": 0.0,
						"healing_done_ultimate": 0.0,
						"instance_id": 1.0,
						"kills": 1.0,
						"shielding_done": 0.0,
						"shielding_done_ability": 0.0,
						"shielding_done_auto": 0.0,
						"shielding_done_passive": 0.0,
						"shielding_done_ultimate": 0.0,
						"stuns": 0.0,
						"team": "player",
						"telemetry": {
							"hard_cc_seconds": 2.0000000000000004,
							"schema": "teamfight.telemetry.v1"
						},
						"ultimates": 0.0,
						"won": false
					},
					{
						"abilities": 7.0,
						"archetype": "monk",
						"assists": 0.0,
						"auto_attacks": 16.0,
						"damage_dealt": 658.9539000000002,
						"damage_dealt_ability": 257.03999999999996,
						"damage_dealt_auto": 367.1999999999999,
						"damage_dealt_passive": 0.0,
						"damage_dealt_ultimate": 34.7139,
						"damage_mitigated": 146.74000000000004,
						"damage_received": 456.1805528667685,
						"deaths": 1.0,
						"healing_done": 0.0,
						"healing_done_ability": 0.0,
						"healing_done_auto": 0.0,
						"healing_done_passive": 0.0,
						"healing_done_ultimate": 0.0,
						"instance_id": 2.0,
						"kills": 3.0,
						"shielding_done": 75.0,
						"shielding_done_ability": 0.0,
						"shielding_done_auto": 0.0,
						"shielding_done_passive": 0.0,
						"shielding_done_ultimate": 75.0,
						"stuns": 5.0,
						"team": "enemy",
						"telemetry": {
							"hard_cc_seconds": 0.0,
							"schema": "teamfight.telemetry.v1"
						},
						"ultimates": 0.0,
						"won": true
					}
				],
				"winner_team": "enemy"
			}
		},
		{
			"input": {
				"enemy_units": [
					{
						"archetype_id": "warlock",
						"team": "enemy",
						"x": 8.0,
						"y": 4.5
					},
					{
						"archetype_id": "siren",
						"team": "enemy",
						"x": 8.4,
						"y": 5.5
					}
				],
				"player_units": [
					{
						"archetype_id": "necromancer",
						"team": "player",
						"x": 2.0,
						"y": 4.5
					},
					{
						"archetype_id": "mistcaller",
						"team": "player",
						"x": 1.6,
						"y": 5.5
					}
				],
				"record_events": false,
				"seed": 909.0,
				"tick_rate": 0.1
			},
			"name": "summoner_support_skirmish",
			"signature": "34752dc8744d373184b87b7db3ea0047f62ea8c1444bf5b8ffa39ca8c1a4bacf",
			"summary": {
				"duration": 60.0,
				"enemy_comp": [
					"warlock",
					"siren"
				],
				"player_comp": [
					"necromancer",
					"mistcaller"
				],
				"seed": 909.0,
				"sudden_death_ticks": 0.0,
				"unit_stats": [
					{
						"abilities": 5.0,
						"archetype": "necromancer",
						"assists": 3.0,
						"auto_attacks": 32.0,
						"damage_dealt": 249.79000000000005,
						"damage_dealt_ability": 0.0,
						"damage_dealt_auto": 249.79000000000005,
						"damage_dealt_passive": 0.0,
						"damage_dealt_ultimate": 0.0,
						"damage_mitigated": 46.875,
						"damage_received": 140.625,
						"deaths": 0.0,
						"healing_done": 0.0,
						"healing_done_ability": 0.0,
						"healing_done_auto": 0.0,
						"healing_done_passive": 0.0,
						"healing_done_ultimate": 0.0,
						"instance_id": 1.0,
						"kills": 0.0,
						"shielding_done": 0.0,
						"shielding_done_ability": 0.0,
						"shielding_done_auto": 0.0,
						"shielding_done_passive": 0.0,
						"shielding_done_ultimate": 0.0,
						"stuns": 0.0,
						"team": "player",
						"telemetry": {
							"hard_cc_seconds": 0.0,
							"schema": "teamfight.telemetry.v1"
						},
						"ultimates": 0.0,
						"won": true
					},
					{
						"abilities": 5.0,
						"archetype": "mistcaller",
						"assists": 7.0,
						"auto_attacks": 23.0,
						"damage_dealt": 249.21,
						"damage_dealt_ability": 0.0,
						"damage_dealt_auto": 249.21,
						"damage_dealt_passive": 0.0,
						"damage_dealt_ultimate": 0.0,
						"damage_mitigated": 19.764000000000003,
						"damage_received": 309.6360000000002,
						"deaths": 1.0,
						"healing_done": 230.14478008935927,
						"healing_done_ability": 29.111663871384284,
						"healing_done_auto": 0.0,
						"healing_done_passive": 39.03311621797492,
						"healing_done_ultimate": 161.99999999999994,
						"instance_id": 2.0,
						"kills": 0.0,
						"shielding_done": 0.0,
						"shielding_done_ability": 0.0,
						"shielding_done_auto": 0.0,
						"shielding_done_passive": 0.0,
						"shielding_done_ultimate": 0.0,
						"stuns": 0.0,
						"team": "player",
						"telemetry": {
							"hard_cc_seconds": 2.000000000000001,
							"schema": "teamfight.telemetry.v1"
						},
						"ultimates": 0.0,
						"won": true
					},
					{
						"abilities": 8.0,
						"archetype": "warlock",
						"assists": 0.0,
						"auto_attacks": 9.0,
						"damage_dealt": 2083.124999999999,
						"damage_dealt_ability": 1954.874999999999,
						"damage_dealt_auto": 128.25,
						"damage_dealt_passive": 0.0,
						"damage_dealt_ultimate": 0.0,
						"damage_mitigated": 236.7000000000003,
						"damage_received": 1341.3000000000015,
						"deaths": 2.0,
						"healing_done": 730.0312499999998,
						"healing_done_ability": 730.0312499999998,
						"healing_done_auto": 0.0,
						"healing_done_passive": 0.0,
						"healing_done_ultimate": 0.0,
						"instance_id": 3.0,
						"kills": 0.0,
						"shielding_done": 0.0,
						"shielding_done_ability": 0.0,
						"shielding_done_auto": 0.0,
						"shielding_done_passive": 0.0,
						"shielding_done_ultimate": 0.0,
						"stuns": 0.0,
						"team": "enemy",
						"telemetry": {
							"hard_cc_seconds": 0.0,
							"schema": "teamfight.telemetry.v1"
						},
						"ultimates": 0.0,
						"won": false
					},
					{
						"abilities": 6.0,
						"archetype": "siren",
						"assists": 0.0,
						"auto_attacks": 33.0,
						"damage_dealt": 494.5460000000003,
						"damage_dealt_ability": 0.0,
						"damage_dealt_auto": 391.1700000000002,
						"damage_dealt_passive": 0.0,
						"damage_dealt_ultimate": 103.376,
						"damage_mitigated": 15.36,
						"damage_received": 368.6400000000001,
						"deaths": 2.0,
						"healing_done": 0.0,
						"healing_done_ability": 0.0,
						"healing_done_auto": 0.0,
						"healing_done_passive": 0.0,
						"healing_done_ultimate": 0.0,
						"instance_id": 4.0,
						"kills": 1.0,
						"shielding_done": 0.0,
						"shielding_done_ability": 0.0,
						"shielding_done_auto": 0.0,
						"shielding_done_passive": 0.0,
						"shielding_done_ultimate": 0.0,
						"stuns": 8.0,
						"team": "enemy",
						"telemetry": {
							"hard_cc_seconds": 0.0,
							"schema": "teamfight.telemetry.v1"
						},
						"ultimates": 0.0,
						"won": false
					}
				],
				"winner_team": "player"
			}
		}
	],
	"rules_version": 1,
	"schema_signature": "470e42d819152ed84c1ac4fb7518091a4145d7846f70a0671cf628ec1af03813"
}